Metadata-Version: 2.1
Name: progressbarscreator
Version: 0.0.1
Summary: Create progress bars in your console
Home-page: UNKNOWN
Author: Dominik Krenn
Author-email: <i96774080@gmail.com>
License: UNKNOWN
Keywords: progressbars,marker,bars
Platform: UNKNOWN
Classifier: Development Status :: 1 - Planning
Classifier: Intended Audience :: Developers
Classifier: Programming Language :: Python :: 3
Classifier: Operating System :: Unix
Classifier: Operating System :: MacOS :: MacOS X
Classifier: Operating System :: Microsoft :: Windows
